{
  "format_version": "1.10.0",
  "minecraft:client_entity": {
    "description": {
      "identifier": "reborn:gastly_trained",
      "materials": { 
          "default": "entity_emissive_alpha"
          },
      "textures": {
        "default": "textures/entity/pokemon/gastly",
        "return": "textures/entity/return"
        
 
      },
      "geometry": {
        "default": "geometry.gastly"
      },
      "animations": {

    "chill": "animation.gastly.chill",
    "walk": "animation.gastly.walk",
    "sit": "animation.gastly.sitting",
    "reborn_pokemon_controller": "controller.animation.reborn_pokemon"
      },
      "scripts": {
        "animate": [
          "reborn_pokemon_controller"
        ]
      },
      "render_controllers": [ "controller.render.reborn_pokemon" ],
      "spawn_egg": {
          "texture": "gastly",
        "texture_index": 1
      }
    }
  }
}